ffclip/FFAudioClip.py
ffclip/FFClip.py
ffclip/FFClipParam.py
ffclip/FFClipXfade.py
ffclip/FFCompositeVideoClip.py
ffclip/FFConcatVideoClip.py
ffclip/FFHelper.py
ffclip/FFImageClip.py
ffclip/FFMetaInfo.py
ffclip/FFSubtitlesClip.py
ffclip/FFTextClip.py
ffclip/FFVideoClip.py
ffclip/FFZoompan.py
ffclip/FilterComplexConcatResult.py
ffclip/FilterComplexHelper.py
ffclip/FilterComplexResult.py
ffclip/__init__.py
ffclip/animation/FFAnimation.py
ffclip/animation/__init__.py
py_ffclip-0.0.2.dist-info/LICENSE
py_ffclip-0.0.2.dist-info/METADATA
py_ffclip-0.0.2.dist-info/WHEEL
py_ffclip-0.0.2.dist-info/top_level.txt
py_ffclip-0.0.2.dist-info/RECORD
