Metadata-Version: 2.1
Name: py-ffclip
Version: 0.0.2
Summary: 基于python封装的ffmpeg视频处理工具，依赖ffmpeg命令行
Home-page: 
Author: kangkang
Author-email: chenwk.top@foxmail.com
Classifier: Programming Language :: Python :: 3
Classifier: License :: OSI Approved :: MIT License
Classifier: Operating System :: OS Independent
Requires-Python: >=3.8
License-File: LICENSE
Requires-Dist: pydub >=0.25.1
